package/__init__.py
package/data.py
package/main.py
package/question_model.py
package/quiz_brain.py
karys_quiz-0.1.0.dist-info/METADATA
karys_quiz-0.1.0.dist-info/WHEEL
karys_quiz-0.1.0.dist-info/entry_points.txt
karys_quiz-0.1.0.dist-info/top_level.txt
karys_quiz-0.1.0.dist-info/RECORD
